tflash/__init__.py
tflash/mscoco_label_map.txt
tflash/roboto.ttf
tflash/string_int_label_map_pb2.py
tflash/visualization_utils.py
tflash-0.5.1.dist-info/LICENSE
tflash-0.5.1.dist-info/METADATA
tflash-0.5.1.dist-info/WHEEL
tflash-0.5.1.dist-info/top_level.txt
tflash-0.5.1.dist-info/RECORD
