Metadata-Version: 2.1
Name: tflash
Version: 0.5.1
Summary: Quick detection practice for images and videos using TensorFlow
Home-page: https://github.com/nuggfr/tflash
Author: Nugroho Fredivianus
Author-email: nuggfr@gmail.com
License: MIT
Keywords: machine learning,tensorflow,object detection
Platform: UNKNOWN
Classifier: Programming Language :: Python :: 3
Classifier: Topic :: Scientific/Engineering :: Artificial Intelligence
Classifier: License :: OSI Approved :: MIT License
Classifier: Operating System :: OS Independent
License-File: LICENSE
Requires-Dist: tensorflow
Requires-Dist: imageio
Requires-Dist: tqdm
